qxmt/__init__.py
qxmt/ansatze/__init__.py
qxmt/ansatze/base.py
qxmt/ansatze/builder.py
qxmt/ansatze/pennylane/__init__.py
qxmt/ansatze/pennylane/all_singles_doubles.py
qxmt/ansatze/pennylane/gete_fabric.py
qxmt/ansatze/pennylane/kupccgsd.py
qxmt/ansatze/pennylane/particle_conserving_u1.py
qxmt/ansatze/pennylane/particle_conserving_u2.py
qxmt/ansatze/pennylane/uccsd.py
qxmt/configs.py
qxmt/constants.py
qxmt/datasets/__init__.py
qxmt/datasets/builder.py
qxmt/datasets/file/__init__.py
qxmt/datasets/file/loader.py
qxmt/datasets/generate/__init__.py
qxmt/datasets/generate/linear.py
qxmt/datasets/generate/loader.py
qxmt/datasets/openml/__init__.py
qxmt/datasets/openml/loader.py
qxmt/datasets/raw_preprocess/__init__.py
qxmt/datasets/raw_preprocess/filter.py
qxmt/datasets/raw_preprocess/sampling.py
qxmt/datasets/schema.py
qxmt/datasets/transform/__init__.py
qxmt/datasets/transform/normalizer.py
qxmt/datasets/transform/reducer.py
qxmt/decorators.py
qxmt/devices/__init__.py
qxmt/devices/amazon.py
qxmt/devices/amazon_device.py
qxmt/devices/base.py
qxmt/devices/builder.py
qxmt/devices/device_info.py
qxmt/devices/ibmq.py
qxmt/devices/ibmq_device.py
qxmt/devices/pennylane_device.py
qxmt/evaluation/__init__.py
qxmt/evaluation/evaluation.py
qxmt/evaluation/metrics/__init__.py
qxmt/evaluation/metrics/base.py
qxmt/evaluation/metrics/defaults_classification.py
qxmt/evaluation/metrics/defaults_regression.py
qxmt/evaluation/metrics/defaults_vqe.py
qxmt/exceptions.py
qxmt/experiment/__init__.py
qxmt/experiment/evaluation_factory.py
qxmt/experiment/executor.py
qxmt/experiment/experiment.py
qxmt/experiment/repository.py
qxmt/experiment/reproducer.py
qxmt/experiment/schema.py
qxmt/feature_maps/__init__.py
qxmt/feature_maps/base.py
qxmt/feature_maps/pennylane/__init__.py
qxmt/feature_maps/pennylane/ising.py
qxmt/feature_maps/pennylane/npqc.py
qxmt/feature_maps/pennylane/rotation.py
qxmt/feature_maps/pennylane/yzcx.py
qxmt/generators/__init__.py
qxmt/generators/description.py
qxmt-0.5.10.dist-info/LICENSE
qxmt-0.5.10.dist-info/METADATA
qxmt-0.5.10.dist-info/WHEEL
qxmt-0.5.10.dist-info/RECORD
