Metadata-Version: 2.1
Name: qxmt
Version: 0.5.10
Summary: QXMT is a experiment management tool for quantum computing and quantum machine learning.
Home-page: https://github.com/kenya-sk/qxmt
License: MIT
Author: kenya-sk
Requires-Python: >=3.10,<3.13
Classifier: License :: OSI Approved :: MIT License
Classifier: Programming Language :: Python :: 3
Classifier: Programming Language :: Python :: 3.10
Classifier: Programming Language :: Python :: 3.11
Classifier: Programming Language :: Python :: 3.12
Provides-Extra: llm
Requires-Dist: aiohttp (>=3.11.16,<4.0.0)
Requires-Dist: amazon-braket-pennylane-plugin (>=1.31.2,<2.0.0)
Requires-Dist: amazon-braket-sdk (>=1.90.2,<2.0.0)
Requires-Dist: autoray (<0.7.0)
Requires-Dist: dill (>=0.3.8,<0.4.0)
Requires-Dist: fsspec (>=2025.3.2,<2026.0.0)
Requires-Dist: h5py (>=3.12.1,<4.0.0)
Requires-Dist: matplotlib (>=3.9.1,<4.0.0)
Requires-Dist: numpy (>=2.0.0,<2.1.0)
Requires-Dist: openml (>=0.15.0,<0.16.0)
Requires-Dist: optuna (>=4.0.0,<5.0.0)
Requires-Dist: pandas (>=2.2.2,<3.0.0)
Requires-Dist: pennylane (>=0.39.0,<0.40.0)
Requires-Dist: pennylane-qiskit (>=0.39.1,<0.40.0)
Requires-Dist: pydantic (>=2.8.2,<3.0.0)
Requires-Dist: pyscf (>=2.8.0,<3.0.0)
Requires-Dist: pyyaml (>=6.0.2,<7.0.0)
Requires-Dist: qiskit (>=1.2.4,<2.0.0)
Requires-Dist: qiskit-aer (==0.17.1)
Requires-Dist: qiskit-ibm-runtime (==0.29)
Requires-Dist: rich[jupyter] (>=13.9.4,<14.0.0)
Requires-Dist: scikit-learn (>=1.5.1,<2.0.0)
Requires-Dist: scipy (>=1.15.2,<2.0.0)
Requires-Dist: seaborn (>=0.13.2,<0.14.0)
Requires-Dist: torch (>=2.4.0,<3.0.0) ; extra == "llm"
Requires-Dist: transformers (>=4.44.2,<5.0.0) ; extra == "llm"
Project-URL: Repository, https://github.com/kenya-sk/qxmt
